{"batchIndex": 22, "totalBatches": 22, "files": [{"path": "packages/graphql-client/src/queries/nodes/nodes.graphql", "language": "graphql", "sizeLines": 76, "fileCategory": "data"}, {"path": "packages/graphql-client/src/queries/roadmaps/roadmaps.graphql", "language": "graphql", "sizeLines": 96, "fileCategory": "data"}, {"path": "packages/graphql-client/src/queries/search.graphql", "language": "graphql", "sizeLines": 14, "fileCategory": "data"}, {"path": "packages/graphql-client/tsconfig.json", "language": "json", "sizeLines": 9, "fileCategory": "config"}, {"path": "packages/lesson/package.json", "language": "json", "sizeLines": 34, "fileCategory": "config"}, {"path": "packages/lesson/src/index.ts", "language": "typescript", "sizeLines": 30, "fileCategory": "code"}, {"path": "packages/lesson/src/test-setup.ts", "language": "typescript", "sizeLines": 1, "fileCategory": "code"}, {"path": "packages/lesson/tsconfig.json", "language": "json", "sizeLines": 11, "fileCategory": "config"}, {"path": "packages/lesson/vitest.config.ts", "language": "typescript", "sizeLines": 11, "fileCategory": "code"}, {"path": "packages/ui/package.json", "language": "json", "sizeLines": 19, "fileCategory": "config"}, {"path": "packages/ui/src/Button.tsx", "language": "typescript", "sizeLines": 53, "fileCategory": "code"}, {"path": "packages/ui/src/Card.tsx", "language": "typescript", "sizeLines": 38, "fileCategory": "code"}, {"path": "packages/ui/src/index.ts", "language": "typescript", "sizeLines": 6, "fileCategory": "code"}, {"path": "packages/ui/src/NodeBadge.tsx", "language": "typescript", "sizeLines": 23, "fileCategory": "code"}, {"path": "packages/ui/tsconfig.json", "language": "json", "sizeLines": 9, "fileCategory": "config"}, {"path": "scripts/validate-yaml.cjs", "language": "javascript", "sizeLines": 31, "fileCategory": "code"}, {"path": "services/svc-python/README.md", "language": "markdown", "sizeLines": 6, "fileCategory": "docs"}, {"path": "services/svc-rust/README.md", "language": "markdown", "sizeLines": 6, "fileCategory": "docs"}], "fileLines": ["1. `packages/graphql-client/src/queries/nodes/nodes.graphql` (76 lines, language: `graphql`, fileCategory: `data`)", "2. `packages/graphql-client/src/queries/roadmaps/roadmaps.graphql` (96 lines, language: `graphql`, fileCategory: `data`)", "3. `packages/graphql-client/src/queries/search.graphql` (14 lines, language: `graphql`, fileCategory: `data`)", "4. `packages/graphql-client/tsconfig.json` (9 lines, language: `json`, fileCategory: `config`)", "5. `packages/lesson/package.json` (34 lines, language: `json`, fileCategory: `config`)", "6. `packages/lesson/src/index.ts` (30 lines, language: `typescript`, fileCategory: `code`)", "7. `packages/lesson/src/test-setup.ts` (1 lines, language: `typescript`, fileCategory: `code`)", "8. `packages/lesson/tsconfig.json` (11 lines, language: `json`, fileCategory: `config`)", "9. `packages/lesson/vitest.config.ts` (11 lines, language: `typescript`, fileCategory: `code`)", "10. `packages/ui/package.json` (19 lines, language: `json`, fileCategory: `config`)", "11. `packages/ui/src/Button.tsx` (53 lines, language: `typescript`, fileCategory: `code`)", "12. `packages/ui/src/Card.tsx` (38 lines, language: `typescript`, fileCategory: `code`)", "13. `packages/ui/src/index.ts` (6 lines, language: `typescript`, fileCategory: `code`)", "14. `packages/ui/src/NodeBadge.tsx` (23 lines, language: `typescript`, fileCategory: `code`)", "15. `packages/ui/tsconfig.json` (9 lines, language: `json`, fileCategory: `config`)", "16. `scripts/validate-yaml.cjs` (31 lines, language: `javascript`, fileCategory: `code`)", "17. `services/svc-python/README.md` (6 lines, language: `markdown`, fileCategory: `docs`)", "18. `services/svc-rust/README.md` (6 lines, language: `markdown`, fileCategory: `docs`)"], "batchImportData": {"packages/graphql-client/src/queries/nodes/nodes.graphql": [], "packages/graphql-client/src/queries/roadmaps/roadmaps.graphql": [], "packages/graphql-client/src/queries/search.graphql": [], "packages/graphql-client/tsconfig.json": [], "packages/lesson/package.json": [], "packages/lesson/src/index.ts": [], "packages/lesson/src/test-setup.ts": [], "packages/lesson/tsconfig.json": [], "packages/lesson/vitest.config.ts": [], "packages/ui/package.json": [], "packages/ui/src/Button.tsx": [], "packages/ui/src/Card.tsx": ["packages/ui/src/NodeBadge.tsx"], "packages/ui/src/index.ts": [], "packages/ui/src/NodeBadge.tsx": [], "packages/ui/tsconfig.json": [], "scripts/validate-yaml.cjs": [], "services/svc-python/README.md": [], "services/svc-rust/README.md": []}, "neighborMap": {}}